train_test_plot_def/__init__.py
train_test_plot_def/train_test_plot_def.py
train_test_plot_def-1.1.0.dist-info/LICENSE
train_test_plot_def-1.1.0.dist-info/METADATA
train_test_plot_def-1.1.0.dist-info/WHEEL
train_test_plot_def-1.1.0.dist-info/top_level.txt
train_test_plot_def-1.1.0.dist-info/RECORD
